{
  "doc_id": "PRA-legal-instruments-2018",
  "title": "PRA Legal Instruments - 2018",
  "short_title": "PRA Legal Instruments - 2018",
  "document_class": "legal_instrument",
  "source_type": "html",
  "raw_path": null,
  "canonical_json_path": null,
  "raw_sha256": "b839655ae48561ee0fff825e6663cd66bd7ab2e5d8c95c85bdfe501577fa11bc",
  "parser_version": "pra-scraper-v1.0.0",
  "quality_score": 1.0,
  "regulator": "PRA",
  "regulator_acronym": "PRA",
  "doc_family_id": "PRA.legal_instruments",
  "version_id": "",
  "version_label": "",
  "version_sort_key": "9999-12-31",
  "guideline_number": "Legal Instruments",
  "status": "active",
  "current_version_flag": true,
  "effective_date_start": null,
  "effective_date_end": null,
  "authority_class": "primary_normative",
  "authority_level": 1,
  "nova_tier": 1,
  "jurisdiction": "United Kingdom",
  "sector": "Banking",
  "supersedes_doc_id": null,
  "superseded_by_doc_id": null,
  "contains_definition": false,
  "contains_formula": false,
  "contains_requirement": true,
  "source_url": "",
  "pra_metadata": {},
  "content_markdown": "# PRA Legal Instruments - 2018\n\n**Total:** 25\n\n- **PRA2018/25**: PRA Rulebook: CRR Firms; Non CRR Firms: Branch Rules Instrument 2018 (Published: 18/12/2018)\n- **PRA2018/24**: PRA Rulebook: CRR Firms: Regulatory Reporting (Amendment) Instrument 2018 (Published: 05/12/2018)\n- **PRA2018/23**: PRA Rulebook: CRR Firms: Leverage Ratio (Amendment) Instrument 2018 (Published: 14/11/2018)\n- **PRA2018/22**: PRA Rulebook: Solvency II Firms and Non Solvency II Firms: Senior Insurance Managers Regime (Amendment) (No 3) Instrument 2018 (Published: 09/11/2018)\n- **PRA2018/21**: PRA Rulebook: CRR Firms, Non CRR Firms, Solvency II Firms and Non Solvency II Firms: Senior Managers Regime and Senior Insurance Managers Regime (Amendment) (No 2) Instrument 2018 (Published: 18/10/2018)\n- **PRA2018/20**: PRA Rulebook: Solvency II Firms and Non-Authorised Persons: External Audit Amendments Instrument 2018 (Published: 17/10/2018)\n- **PRA2018/19**: PRA Rulebook: Solvency II Reporting Amendments Instrument (No.2) 2018 (Published: 26/07/2018)\n- **PRA2018/18**: PRA Rulebook: Change in Control Amendments Instrument (No.1) 2018 (Published: 06/07/2018)\n- **PRA2018/17**: PRA Rulebook: Solvency II Firms: Reporting Amendments Instrument (No.1) 2018 (Published: 06/07/2018)\n- **PRA2018/16**: PRA Rulebook: CRR Firms, Non-CRR Firms, Solvency II Firms and Non Solvency II Firms: Senior Managers Regime and Senior Insurance Managers Regime (Amendment) (No 1) Instrument 2018 (Published: 04/07/2018)\n- **PRA2018/15**: PRA Rulebook: CRR Firms: Benchmarking Regulation Instrument 2018 (Published: 29/06/2018)\n- **PRA2018/12**: PRA Rulebook: MIFID II Passporting Amendment Instrument 2018 (Published: 29/06/2018)\n- **PRA2018/2**: PRA Rulebook: CRR Firms, Non CRR Firms, Solvency II Firms, Non Solvency II Firms: MiFid II Passporting and IDD Consequential Amendments Instrument 2018 (Published: 29/06/2018)\n- **PRA2018/14**: PRA Rulebook: CRR Firms: Large Exposures Amendment Instrument 2018 (Published: 28/06/2018)\n- **PRA2018/13**: PRA Rulebook: PRA Periodic Fees (2018/19) and Other Fees Instrument 2018 (Published: 28/06/2018)\n- **PRA2018/11**: PRA Rulebook: CRR Firm Internal Capital Adequacy Assessment (No. 2) Instrument 2018 (Published: 30/04/2018)\n- **PRA2018/10**: PRA Rulebook: CRR Firms: Reporting Pillar 2 Amendment No.1 Instrument 2018 (Published: 30/04/2018)\n- **PRA2018/9**: PRA Rulebook: CRR Firms: Whistleblowing Amendment  Instrument 2018 (Published: 29/03/2018)\n- **PRA2018/8**: PRA Rulebook: CRR Firms: Groups (Level of Application) Instrument 2018 (Published: 29/03/2018)\n- **PRA2018/7**: PRA Rulebook: Solvency II Firms: Transitional Measures: Report on Financial and Solvency Conditions Instrument 2018 (Published: 29/03/2018)\n- **PRA2018/6**: PRA Rulebook: CRR Firms: Internal Capital Adequacy Assessment (Amendment) Instrument 2018 (Published: 29/03/2018)\n- **PRA2018/5**: PRA Rulebook: Solvency II Firms: Conditions Governing Business Instrument 2018 (Published: 29/03/2018)\n- **PRA2018/4**: PRA Rulebook: Non Authorised Persons: FSCS Management Expenses Levy Limit and Base Costs Instrument 2018 (Published: 29/03/2018)\n- **PRA2018/3**: PRA Rulebook: CRR Firms: Regulatory Reporting PRA110 Amendment Instrument 2018 (Published: 23/02/2018)\n- **PRA2018/1**: PRA Rulebook: Solvency II Firms, Non-Solvency II Firms: Senior Insurance Managers Regime (Amendment) Instrument 2018 (Published: 07/02/2018)",
  "content_html": "<h1>Legal Instruments 2018</h1><p>25 instruments</p>"
}