{
  "doc_id": "PRA-BOE-ss2415-jan-2022",
  "title": "SS2415/ – Ss2415 Jan 2022",
  "short_title": "SS2415/",
  "document_class": "supervisory_statement",
  "regulator": "PRA",
  "jurisdiction": "UK",
  "authority_class": "interpretive",
  "nova_tier": 2,
  "status": "active",
  "effective_date_start": "2021-01-01",
  "guideline_number": "SS2415/",
  "sector": [
    "B",
    "a",
    "g",
    "i",
    "k",
    "n"
  ],
  "source_url": "https://www.bankofengland.co.uk/-/media/boe/files/prudential-regulation/supervisory-statement/2021/ss2415-jan-2022.pdf",
  "source_format": "pdf",
  "pages": 29,
  "pra_parent_documents": [
    "pra.ss2415.2026"
  ],
  "doc_family_id": "PRA-BOE-ss2415-jan-2022",
  "version_id": "2021-01-01",
  "supersedes_doc_id": "",
  "superseded_by_doc_id": "",
  "contains_definition": false,
  "contains_formula": true,
  "contains_requirement": true,
  "sha256": "d7bb917cd6f8f35f369e80e34cff6fd14191a3330670aa5b6772bfeb5f76cdb9",
  "scraped_at": "2026-03-25T03:32:26.960591Z",
  "raw_sha256": "d7bb917cd6f8f35f369e80e34cff6fd14191a3330670aa5b6772bfeb5f76cdb9",
  "regulator_acronym": "PRA",
  "version_label": "January 2021",
  "version_sort_key": "2021-01-01",
  "current_version_flag": true,
  "effective_date_end": null,
  "authority_level": 5,
  "raw_path": null,
  "canonical_json_path": null,
  "parser_version": "boe-scraper-v1.0.0",
  "quality_score": 1.0,
  "heading_path": [
    "SS2415/ – Ss2415 Jan 2022"
  ],
  "section_path": "SS2415/ – Ss2415 Jan 2022",
  "citation_anchor": "PRA-BOE-ss2415-jan-2022::root",
  "section_headings": []
}